[{"authors":["admin"],"categories":null,"content":"I\u0026rsquo;m a network measurement and data analysis researcher. I enjoy working with IoTs, analyzing Internet usage and reliability, and developing solutions to make network usage more secure.\n","date":-62135596800,"expirydate":-62135596800,"kind":"taxonomy","lang":"en","lastmod":-62135596800,"objectID":"2525497d367e79493fd32b198b28f040","permalink":"https://sarthakgrover.github.io/authors/admin/","publishdate":"0001-01-01T00:00:00Z","relpermalink":"/authors/admin/","section":"authors","summary":"I\u0026rsquo;m a network measurement and data analysis researcher. I enjoy working with IoTs, analyzing Internet usage and reliability, and developing solutions to make network usage more secure.","tags":null,"title":"Sarthak Grover","type":"authors"},{"authors":[],"categories":[],"content":"","date":1568825226,"expirydate":-62135596800,"kind":"page","lang":"en","lastmod":1568825226,"objectID":"9ebb016b8f62ea5c22d5e4ba085ce665","permalink":"https://sarthakgrover.github.io/project/my-project-name/","publishdate":"2019-09-18T22:17:06+05:30","relpermalink":"/project/my-project-name/","section":"project","summary":"summary of proj","tags":["Network Measurement","CDN"],"title":"Updating ...","type":"project"}]